{"data": [{"category": "2.6", "downloads": 14}, {"category": "2.7", "downloads": 1528774}, {"category": "3.10", "downloads": 5576}, {"category": "3.2", "downloads": 2}, {"category": "3.3", "downloads": 173}, {"category": "3.4", "downloads": 11161}, {"category": "3.5", "downloads": 954048}, {"category": "3.6", "downloads": 3551707}, {"category": "3.7", "downloads": 7434023}, {"category": "3.8", "downloads": 5433866}, {"category": "3.9", "downloads": 742470}, {"category": "null", "downloads": 570281}], "package": "attrs", "type": "python_minor_downloads"}
