{"last_update":"2022-07-15 13:54:49","query":{"bytes_billed":449839104,"bytes_processed":449717209,"cached":false,"estimated_cost":"0.01"},"rows":[{"download_count":1330926,"percent":"0.9","python_version":"2.7"},{"download_count":52951,"percent":"0.036","python_version":"3.5"},{"download_count":37646,"percent":"0.026","python_version":"3.6"},{"download_count":34286,"percent":"0.023","python_version":"3.4"},{"download_count":17466,"percent":"0.012","python_version":"2.6"},{"download_count":2715,"percent":"0.0018","python_version":"3.3"},{"download_count":197,"percent":"0.00013","python_version":"3.2"},{"download_count":71,"percent":"4.8e-05","python_version":"3.7"},{"download_count":55,"percent":"3.7e-05","python_version":"None"}]}
