{"data": [{"category": "2.7", "downloads": 1175714}, {"category": "2.8", "downloads": 2}, {"category": "3.10", "downloads": 100253039}, {"category": "3.11", "downloads": 81393825}, {"category": "3.12", "downloads": 60061633}, {"category": "3.13", "downloads": 20225548}, {"category": "3.14", "downloads": 23852}, {"category": "3.15", "downloads": 312}, {"category": "3.2", "downloads": 1}, {"category": "3.3", "downloads": 31}, {"category": "3.4", "downloads": 16185}, {"category": "3.5", "downloads": 62858}, {"category": "3.6", "downloads": 2883910}, {"category": "3.7", "downloads": 24248919}, {"category": "3.8", "downloads": 25835987}, {"category": "3.9", "downloads": 59394345}, {"category": "null", "downloads": 14958925}], "package": "cryptography", "type": "python_minor_downloads"}
