{"last_update":"2024-11-01 22:34:50","query":{"bytes_billed":926941184,"bytes_processed":926129528,"cached":false,"estimated_cost":"0.01"},"rows":[{"download_count":163885,"percent":"0.45","python_version":"3.8"},{"download_count":77754,"percent":"0.21","python_version":"3.6"},{"download_count":65912,"percent":"0.18","python_version":"3.7"},{"download_count":44721,"percent":"0.12","python_version":"3.9"},{"download_count":8335,"percent":"0.023","python_version":"2.7"},{"download_count":4184,"percent":"0.011","python_version":"3.10"},{"download_count":2814,"percent":"0.0077","python_version":"3.5"},{"download_count":19,"percent":"5.2e-05","python_version":"3.4"},{"download_count":6,"percent":"1.6e-05","python_version":"3.11"}]}
