{"data": [{"category": "2.6", "downloads": 1175}, {"category": "2.7", "downloads": 1342747}, {"category": "3.2", "downloads": 9}, {"category": "3.3", "downloads": 88}, {"category": "3.4", "downloads": 53017}, {"category": "3.5", "downloads": 283434}, {"category": "3.6", "downloads": 1654531}, {"category": "3.7", "downloads": 1762579}, {"category": "3.8", "downloads": 65598}, {"category": "3.9", "downloads": 25}, {"category": "null", "downloads": 25357}], "package": "flake8", "type": "python_minor_downloads"}
