{"last_update":"2023-01-30 07:25:00","query":{"bytes_billed":123731968,"bytes_processed":122705992,"cached":false,"estimated_cost":"0.01"},"rows":[{"download_count":107849,"percent":"0.8","python_version":"2.7"},{"download_count":12993,"percent":"0.096","python_version":"3.4"},{"download_count":7755,"percent":"0.057","python_version":"3.5"},{"download_count":4934,"percent":"0.037","python_version":"2.6"},{"download_count":1031,"percent":"0.0076","python_version":"3.3"},{"download_count":153,"percent":"0.0011","python_version":"3.2"},{"download_count":109,"percent":"0.00081","python_version":"3.6"},{"download_count":59,"percent":"0.00044","python_version":"None"}]}
