{"last_update":"2021-08-17 10:56:15","query":{"bytes_billed":722468864,"bytes_processed":721852972,"cached":false,"estimated_cost":"0.01"},"rows":[{"download_count":891406,"percent":"0.67","python_version":"2.7"},{"download_count":184693,"percent":"0.14","python_version":"3.5"},{"download_count":152276,"percent":"0.11","python_version":"3.6"},{"download_count":95955,"percent":"0.072","python_version":"3.4"},{"download_count":1435,"percent":"0.0011","python_version":"3.3"},{"download_count":868,"percent":"0.00065","python_version":"2.6"},{"download_count":681,"percent":"0.00051","python_version":"3.7"},{"download_count":70,"percent":"5.3e-05","python_version":"3.2"},{"download_count":9,"percent":"6.8e-06","python_version":"None"}]}
