{"last_update":"2021-01-10 22:08:00","query":{"bytes_billed":12169773056,"bytes_processed":12169594077,"cached":false,"estimated_cost":"0.06"},"rows":[{"download_count":51151,"percent":"0.66","python_version":"2.7"},{"download_count":12663,"percent":"0.16","python_version":"3.6"},{"download_count":8798,"percent":"0.11","python_version":"3.5"},{"download_count":4842,"percent":"0.062","python_version":"3.4"},{"download_count":154,"percent":"0.002","python_version":"3.7"},{"download_count":40,"percent":"0.00052","python_version":"2.6"},{"download_count":16,"percent":"0.00021","python_version":"3.3"},{"download_count":1,"percent":"1.3e-05","python_version":"None"}]}
