{"last_update":"2021-01-25 15:34:32","query":{"bytes_billed":793772032,"bytes_processed":793078815,"cached":false,"estimated_cost":"0.01"},"rows":[{"download_count":88162,"percent":"0.87","python_version":"2.7"},{"download_count":9085,"percent":"0.09","python_version":"3.5"},{"download_count":3155,"percent":"0.031","python_version":"3.4"},{"download_count":454,"percent":"0.0045","python_version":"3.3"},{"download_count":167,"percent":"0.0017","python_version":"2.6"},{"download_count":135,"percent":"0.0013","python_version":"3.6"},{"download_count":6,"percent":"5.9e-05","python_version":"3.2"},{"download_count":3,"percent":"3e-05","python_version":"3.7"}]}
