{"last_update":"2024-03-04 13:08:52","query":{"bytes_billed":434110464,"bytes_processed":433425823,"cached":false,"estimated_cost":"0.01"},"rows":[{"download_count":149207,"percent":"0.66","python_version":"2.7"},{"download_count":37631,"percent":"0.17","python_version":"3.5"},{"download_count":32004,"percent":"0.14","python_version":"3.4"},{"download_count":4580,"percent":"0.02","python_version":"3.3"},{"download_count":975,"percent":"0.0043","python_version":"2.6"},{"download_count":708,"percent":"0.0031","python_version":"3.2"},{"download_count":585,"percent":"0.0026","python_version":"3.6"},{"download_count":23,"percent":"0.0001","python_version":"None"}]}
