{"last_update":"2018-08-01 10:09:36","query":{"bytes_billed":15627976704,"bytes_processed":15627125982,"cached":false,"estimated_cost":"0.08"},"rows":[{"download_count":1339599,"percent":"0.71","python_version":"2.7"},{"download_count":326026,"percent":"0.17","python_version":"3.5"},{"download_count":126649,"percent":"0.067","python_version":"3.6"},{"download_count":82749,"percent":"0.044","python_version":"3.4"},{"download_count":13154,"percent":"0.007","python_version":"2.6"},{"download_count":1726,"percent":"0.00091","python_version":"3.3"},{"download_count":315,"percent":"0.00017","python_version":"3.2"},{"download_count":215,"percent":"0.00011","python_version":"3.7"},{"download_count":69,"percent":"3.6e-05","python_version":"None"}]}
