{"data": [{"category": "2.6", "downloads": 2362}, {"category": "2.7", "downloads": 2653816}, {"category": "3.10", "downloads": 442}, {"category": "3.2", "downloads": 32}, {"category": "3.3", "downloads": 28}, {"category": "3.4", "downloads": 105369}, {"category": "3.5", "downloads": 2120850}, {"category": "3.6", "downloads": 9036223}, {"category": "3.7", "downloads": 8446766}, {"category": "3.8", "downloads": 2251318}, {"category": "3.9", "downloads": 1917}, {"category": "null", "downloads": 144511}], "package": "pandas", "type": "python_minor_downloads"}
