{"data": [{"category": "2.7", "downloads": 312494}, {"category": "3.10", "downloads": 39601030}, {"category": "3.11", "downloads": 57266362}, {"category": "3.12", "downloads": 72135854}, {"category": "3.13", "downloads": 48450024}, {"category": "3.14", "downloads": 9670163}, {"category": "3.15", "downloads": 8332}, {"category": "3.2", "downloads": 3}, {"category": "3.3", "downloads": 21}, {"category": "3.4", "downloads": 490}, {"category": "3.5", "downloads": 13849}, {"category": "3.6", "downloads": 5153565}, {"category": "3.7", "downloads": 11634714}, {"category": "3.8", "downloads": 7476554}, {"category": "3.9", "downloads": 18021547}, {"category": "null", "downloads": 8289850}], "package": "pillow", "type": "python_minor_downloads"}
