{"data": [{"category": "2.7", "downloads": 83869}, {"category": "3.10", "downloads": 3811351}, {"category": "3.11", "downloads": 4240869}, {"category": "3.12", "downloads": 947399}, {"category": "3.13", "downloads": 2626}, {"category": "3.14", "downloads": 12}, {"category": "3.4", "downloads": 69}, {"category": "3.5", "downloads": 18083}, {"category": "3.6", "downloads": 5421602}, {"category": "3.7", "downloads": 630765}, {"category": "3.8", "downloads": 2118840}, {"category": "3.9", "downloads": 1430325}, {"category": "null", "downloads": 732463}], "package": "prettytable", "type": "python_minor_downloads"}
