{"data": [{"category": "2.6", "downloads": 27}, {"category": "2.7", "downloads": 452324}, {"category": "3.10", "downloads": 928981}, {"category": "3.11", "downloads": 2534}, {"category": "3.2", "downloads": 56}, {"category": "3.3", "downloads": 166}, {"category": "3.4", "downloads": 7673}, {"category": "3.5", "downloads": 46347}, {"category": "3.6", "downloads": 1363222}, {"category": "3.7", "downloads": 4329257}, {"category": "3.8", "downloads": 4606878}, {"category": "3.9", "downloads": 3241401}, {"category": "null", "downloads": 2022120}], "package": "pyflakes", "type": "python_minor_downloads"}
