{"last_update":"2019-01-03 20:58:28","query":{"bytes_billed":12518948864,"bytes_processed":12517908738,"cached":false,"estimated_cost":"0.06"},"rows":[{"download_count":417720,"percent":"0.77","python_version":"2.7"},{"download_count":66431,"percent":"0.12","python_version":"3.5"},{"download_count":48267,"percent":"0.089","python_version":"3.4"},{"download_count":4752,"percent":"0.0087","python_version":"3.3"},{"download_count":3259,"percent":"0.006","python_version":"2.6"},{"download_count":3075,"percent":"0.0056","python_version":"3.6"},{"download_count":659,"percent":"0.0012","python_version":"3.7"},{"download_count":352,"percent":"0.00065","python_version":"3.2"},{"download_count":27,"percent":"5e-05","python_version":"None"}]}
