{"last_update":"2021-10-14 10:09:22","query":{"bytes_billed":887095296,"bytes_processed":886086974,"cached":false,"estimated_cost":"0.01"},"rows":[{"download_count":1952989,"percent":"0.36","python_version":"3.7"},{"download_count":1576225,"percent":"0.29","python_version":"3.6"},{"download_count":640216,"percent":"0.12","python_version":"3.5"},{"download_count":608364,"percent":"0.11","python_version":"3.8"},{"download_count":559566,"percent":"0.1","python_version":"2.7"},{"download_count":14371,"percent":"0.0027","python_version":"3.4"},{"download_count":6948,"percent":"0.0013","python_version":"3.9"},{"download_count":1693,"percent":"0.00032","python_version":"2.6"},{"download_count":382,"percent":"7.1e-05","python_version":"3.3"},{"download_count":1,"percent":"1.9e-07","python_version":"3.2"}]}
