{"last_update":"2021-10-14 10:10:44","query":{"bytes_billed":786432000,"bytes_processed":786330580,"cached":false,"estimated_cost":"0.01"},"rows":[{"download_count":667600,"percent":"0.43","python_version":"3.6"},{"download_count":458396,"percent":"0.29","python_version":"2.7"},{"download_count":209499,"percent":"0.13","python_version":"3.5"},{"download_count":159889,"percent":"0.1","python_version":"3.7"},{"download_count":64058,"percent":"0.041","python_version":"3.4"},{"download_count":2087,"percent":"0.0013","python_version":"2.6"},{"download_count":1415,"percent":"0.0009","python_version":"3.8"},{"download_count":1030,"percent":"0.00066","python_version":"3.3"},{"download_count":30,"percent":"1.9e-05","python_version":"3.2"}]}
