{"data": [{"category": "2.6", "downloads": 14}, {"category": "2.7", "downloads": 814703}, {"category": "3.1", "downloads": 1}, {"category": "3.10", "downloads": 3698740}, {"category": "3.11", "downloads": 51009}, {"category": "3.12", "downloads": 247}, {"category": "3.2", "downloads": 37}, {"category": "3.3", "downloads": 187}, {"category": "3.4", "downloads": 12706}, {"category": "3.5", "downloads": 205723}, {"category": "3.6", "downloads": 4402107}, {"category": "3.7", "downloads": 10473562}, {"category": "3.8", "downloads": 14579557}, {"category": "3.9", "downloads": 8741221}, {"category": "null", "downloads": 3948472}], "package": "pytest", "type": "python_minor_downloads"}
