{"last_update":"2020-01-02 23:01:02","query":{"bytes_billed":1453326336,"bytes_processed":1453253215,"cached":false,"estimated_cost":"0.01"},"rows":[{"download_count":671875,"percent":"0.82","python_version":"2.7"},{"download_count":59683,"percent":"0.073","python_version":"3.4"},{"download_count":39565,"percent":"0.048","python_version":"3.5"},{"download_count":32838,"percent":"0.04","python_version":"2.6"},{"download_count":11380,"percent":"0.014","python_version":"3.3"},{"download_count":1592,"percent":"0.0019","python_version":"3.2"},{"download_count":481,"percent":"0.00059","python_version":"3.6"},{"download_count":240,"percent":"0.00029","python_version":"None"}]}
