{"data": [{"category": "2.6", "downloads": 32}, {"category": "2.7", "downloads": 1290802}, {"category": "3.10", "downloads": 4}, {"category": "3.3", "downloads": 4}, {"category": "3.4", "downloads": 14947}, {"category": "3.5", "downloads": 766173}, {"category": "3.6", "downloads": 3296491}, {"category": "3.7", "downloads": 4889824}, {"category": "3.8", "downloads": 583592}, {"category": "3.9", "downloads": 213}, {"category": "null", "downloads": 48187}], "package": "scikit-learn", "type": "python_minor_downloads"}
