{"data": [{"category": "2.6", "downloads": 377}, {"category": "2.7", "downloads": 5048276}, {"category": "3.2", "downloads": 5}, {"category": "3.3", "downloads": 20}, {"category": "3.4", "downloads": 57070}, {"category": "3.5", "downloads": 2560185}, {"category": "3.6", "downloads": 5176743}, {"category": "3.7", "downloads": 3146979}, {"category": "3.8", "downloads": 313813}, {"category": "3.9", "downloads": 567}, {"category": "null", "downloads": 75035}], "package": "scipy", "type": "python_minor_downloads"}
