{"last_update":"2019-04-04 14:26:20","query":{"bytes_billed":14137950208,"bytes_processed":14137822781,"cached":false,"estimated_cost":"0.07"},"rows":[{"download_count":10184880,"percent":"0.8","python_version":"2.7"},{"download_count":1316247,"percent":"0.1","python_version":"3.6"},{"download_count":606546,"percent":"0.047","python_version":"3.5"},{"download_count":531576,"percent":"0.042","python_version":"3.4"},{"download_count":121832,"percent":"0.0095","python_version":"2.6"},{"download_count":5687,"percent":"0.00045","python_version":"3.3"},{"download_count":5128,"percent":"0.0004","python_version":"3.7"},{"download_count":302,"percent":"2.4e-05","python_version":"None"},{"download_count":178,"percent":"1.4e-05","python_version":"3.2"},{"download_count":27,"percent":"2.1e-06","python_version":"3.8"},{"download_count":8,"percent":"6.3e-07","python_version":"3.1"}]}
