{"last_update":"2021-01-26 15:23:28","query":{"bytes_billed":621805568,"bytes_processed":621262709,"cached":false,"estimated_cost":"0.01"},"rows":[{"download_count":137129,"percent":"0.36","python_version":"3.6"},{"download_count":94638,"percent":"0.25","python_version":"3.7"},{"download_count":89571,"percent":"0.23","python_version":"2.7"},{"download_count":38374,"percent":"0.1","python_version":"3.5"},{"download_count":21763,"percent":"0.057","python_version":"3.8"},{"download_count":2012,"percent":"0.0052","python_version":"3.4"},{"download_count":14,"percent":"3.7e-05","python_version":"3.9"},{"download_count":6,"percent":"1.6e-05","python_version":"2.6"},{"download_count":5,"percent":"1.3e-05","python_version":"3.3"}]}
