{"last_update":"2021-01-26 15:27:11","query":{"bytes_billed":948961280,"bytes_processed":948289775,"cached":false,"estimated_cost":"0.01"},"rows":[{"download_count":58416,"percent":"0.88","python_version":"2.7"},{"download_count":5276,"percent":"0.08","python_version":"3.4"},{"download_count":2167,"percent":"0.033","python_version":"3.5"},{"download_count":133,"percent":"0.002","python_version":"2.6"},{"download_count":120,"percent":"0.0018","python_version":"3.3"},{"download_count":6,"percent":"9.1e-05","python_version":"3.6"},{"download_count":3,"percent":"4.5e-05","python_version":"3.2"},{"download_count":1,"percent":"1.5e-05","python_version":"None"}]}
