{"last_update":"2020-08-17 17:08:03","query":{"bytes_billed":12169773056,"bytes_processed":12169594077,"cached":false,"estimated_cost":"0.06"},"rows":[{"download_count":142573,"percent":"0.43","python_version":"2.7"},{"download_count":116832,"percent":"0.36","python_version":"3.6"},{"download_count":52357,"percent":"0.16","python_version":"3.5"},{"download_count":14655,"percent":"0.045","python_version":"3.4"},{"download_count":1525,"percent":"0.0046","python_version":"3.7"},{"download_count":172,"percent":"0.00052","python_version":"2.6"},{"download_count":166,"percent":"0.00051","python_version":"3.3"},{"download_count":39,"percent":"0.00012","python_version":"3.2"},{"download_count":3,"percent":"9.1e-06","python_version":"3.8"},{"download_count":1,"percent":"3e-06","python_version":"None"}]}
