{"last_update":"2020-12-16 14:48:05","query":{"bytes_billed":47774171136,"bytes_processed":47774133078,"cached":false,"estimated_cost":"0.22"},"rows":[{"download_count":3346312,"percent":"0.61","python_version":"2.7"},{"download_count":854813,"percent":"0.16","python_version":"3.6"},{"download_count":794012,"percent":"0.15","python_version":"3.5"},{"download_count":253451,"percent":"0.047","python_version":"3.7"},{"download_count":110180,"percent":"0.02","python_version":"3.4"},{"download_count":79538,"percent":"0.015","python_version":"2.6"},{"download_count":3872,"percent":"0.00071","python_version":"3.3"},{"download_count":356,"percent":"6.5e-05","python_version":"3.8"},{"download_count":304,"percent":"5.6e-05","python_version":"3.2"},{"download_count":19,"percent":"3.5e-06","python_version":"None"},{"download_count":8,"percent":"1.5e-06","python_version":"3.1"}]}
