{"last_update":"2020-09-21 12:37:28","query":{"bytes_billed":2221932544,"bytes_processed":2221500215,"cached":false,"estimated_cost":"0.02"},"rows":[{"download_count":679043,"percent":"0.92","python_version":"2.7"},{"download_count":29016,"percent":"0.039","python_version":"2.6"},{"download_count":19997,"percent":"0.027","python_version":"3.4"},{"download_count":10138,"percent":"0.014","python_version":"3.5"},{"download_count":2296,"percent":"0.0031","python_version":"3.3"},{"download_count":851,"percent":"0.0011","python_version":"3.6"},{"download_count":323,"percent":"0.00044","python_version":"3.2"},{"download_count":88,"percent":"0.00012","python_version":"None"}]}
